libpytools_teste
